no_cyclic_imports/__init__.py
no_cyclic_imports/__main__.py
no_cyclic_imports/_engine.py
no_cyclic_imports/_imports.py
no_cyclic_imports/_normalization.py
no_cyclic_imports/version.py
no_cyclic_imports/tests/__init__.py
no_cyclic_imports/tests/factories.py
no_cyclic_imports/tests/test_imports.py
no_cyclic_imports/tests/test_main.py
no_cyclic_imports/tests/test_normalization.py
no_cyclic_imports-2.1.0.dist-info/METADATA
no_cyclic_imports-2.1.0.dist-info/WHEEL
no_cyclic_imports-2.1.0.dist-info/entry_points.txt
no_cyclic_imports-2.1.0.dist-info/licenses/COPYING
no_cyclic_imports-2.1.0.dist-info/RECORD
