Metadata-Version: 2.3
Name: no-cyclic-imports
Version: 2.1.0
Summary: Tool to detect and report on cyclic imports in a Python codebase
Project-URL: Homepage, https://github.com/hartwork/no-cyclic-imports
Author-email: Sebastian Pipping <sebastian@pipping.org>
License: AGPL-3.0-or-later
License-File: COPYING
Keywords: automation,lint,linter
Classifier: Development Status :: 4 - Beta
Classifier: Programming Language :: Python
Classifier: Programming Language :: Python :: 3
Classifier: Programming Language :: Python :: 3 :: Only
Classifier: Programming Language :: Python :: 3.10
Classifier: Programming Language :: Python :: 3.11
Classifier: Programming Language :: Python :: 3.12
Classifier: Programming Language :: Python :: Implementation :: CPython
Requires-Python: >=3.10
Requires-Dist: import-deps
Requires-Dist: networkx
Requires-Dist: stdlib-list
Provides-Extra: tests
Requires-Dist: coverage; extra == 'tests'
Requires-Dist: parameterized; extra == 'tests'
Requires-Dist: pytest; extra == 'tests'
